{
  "hash": "3e55ac93",
  "configHash": "1dc782e8",
  "lockfileHash": "99866c79",
  "browserHash": "add6b87b",
  "optimized": {
    "react": {
      "src": "../../node_modules/react/index.js",
      "file": "react.js",
      "fileHash": "acba4250",
      "needsInterop": true
    },
    "react-dom/client": {
      "src": "../../node_modules/react-dom/client.js",
      "file": "react-dom_client.js",
      "fileHash": "a0901917",
      "needsInterop": true
    },
    "lucide-react": {
      "src": "../../node_modules/lucide-react/dist/esm/lucide-react.js",
      "file": "lucide-react.js",
      "fileHash": "5cc3f50a",
      "needsInterop": false
    },
    "date-fns": {
      "src": "../../node_modules/date-fns/index.mjs",
      "file": "date-fns.js",
      "fileHash": "df7bc2ee",
      "needsInterop": false
    },
    "xlsx": {
      "src": "../../node_modules/xlsx/xlsx.mjs",
      "file": "xlsx.js",
      "fileHash": "63b3806e",
      "needsInterop": false
    },
    "chart.js": {
      "src": "../../node_modules/chart.js/dist/chart.js",
      "file": "chart__js.js",
      "fileHash": "eee1feb8",
      "needsInterop": false
    },
    "react-chartjs-2": {
      "src": "../../node_modules/react-chartjs-2/dist/index.js",
      "file": "react-chartjs-2.js",
      "fileHash": "0bc7c14a",
      "needsInterop": false
    }
  },
  "chunks": {
    "chunk-TWJRYSII": {
      "file": "chunk-TWJRYSII.js"
    },
    "chunk-R5T4AUMD": {
      "file": "chunk-R5T4AUMD.js"
    },
    "chunk-DC5AMYBS": {
      "file": "chunk-DC5AMYBS.js"
    }
  }
}